deloqv/Algorithme.py
deloqv/MAP.py
deloqv/Pr_dist.py
deloqv/Test.py
deloqv/__init__.py
deloqv/data_cleaning.py
deloqv-0.1.1.dist-info/LICENCE.txt
deloqv-0.1.1.dist-info/METADATA
deloqv-0.1.1.dist-info/WHEEL
deloqv-0.1.1.dist-info/top_level.txt
deloqv-0.1.1.dist-info/RECORD
