Metadata-Version: 2.1
Name: deloqv
Version: 0.1.1
Summary: voir presentation
Home-page: https://github.com/ELKHMISSI/Project.git
Author: EL KHMISSI, NIASSE, FONTANA
Author-email: mohamed.el-khmissi01@etu.umontpellier.fr
Maintainer: EL KHMISSI, NIASSE, FONTANA
Maintainer-email: mohamed.el-khmissi01@etu.umontpellier.fr
License: MIT
Keywords: Prices distances south France highways
Platform: ALL
License-File: LICENCE.txt
